CollapsedGibbsSampler/__init__.py
CollapsedGibbsSampler/cgs.py
CollapsedGibbsSampler/cgs_cython.so
CollapsedGibbsSampler/matutil.so
LDAutil/Evaluation.py
LDAutil/__init__.py
plda-1.0.0.dist-info/DESCRIPTION.rst
plda-1.0.0.dist-info/METADATA
plda-1.0.0.dist-info/RECORD
plda-1.0.0.dist-info/WHEEL
plda-1.0.0.dist-info/metadata.json
plda-1.0.0.dist-info/top_level.txt
util/omp_defs.so
