Metadata-Version: 2.0
Name: plda
Version: 1.0.0
Summary: Latent Dirichlet Allocation in parallel
Home-page: https://github.com/virgodi/plda
Author: Virgile Audi, Charles Liu, Nicolas Drizard
Author-email: vaudi@g.harvard.edu, cliu02@g.harvard.edu , nicolasdrizard@g.harvard.edu
License: MIT
Keywords: topic modeling development
Platform: UNKNOWN
Classifier: Development Status :: 3 - Alpha
Classifier: Intended Audience :: Developers
Classifier: Topic :: Scientific/Engineering :: Information Analysis
Classifier: License :: OSI Approved :: MIT License
Classifier: Programming Language :: Python :: 2
Classifier: Programming Language :: Python :: 2.6
Classifier: Programming Language :: Python :: 2.7
Requires-Dist: cython
Requires-Dist: numpy
